pynovnc/Main.py
pynovnc/__init__.py
pynovnc-1.1.8.dist-info/METADATA
pynovnc-1.1.8.dist-info/WHEEL
pynovnc-1.1.8.dist-info/entry_points.txt
pynovnc-1.1.8.dist-info/top_level.txt
pynovnc-1.1.8.dist-info/RECORD
