Metadata-Version: 2.1
Name: pynovnc
Version: 1.1.8
Summary: Python Package made by Mhadhbi Issam . 
Home-page: https://gitlab.com/isampypi/pynovnc
Author: Mhadhbi Issam
Author-email: mhadhbixissam@gmail.com
Classifier: Programming Language :: Python :: 3
Classifier: License :: OSI Approved :: MIT License
Classifier: Operating System :: OS Independent
Requires-Dist: portpicker
